qtrackcli/__init__.py
qtrackcli/__main__.py
qtrackcli/cli.py
qtrackcli-1.0.0.dist-info/METADATA
qtrackcli-1.0.0.dist-info/WHEEL
qtrackcli-1.0.0.dist-info/entry_points.txt
qtrackcli-1.0.0.dist-info/top_level.txt
qtrackcli-1.0.0.dist-info/RECORD
